Metadata-Version: 2.1
Name: strv-ds-opensearch-manager
Version: 1.0.0
Summary: STRV OpenSearch manager repository.
Home-page: https://github.com/strvcom/strv-ds-opensearch-manager
Author: STRV DS Department <datascience.dept@strv.com>
Author-email: datascience.dept@strv.com
Requires-Python: >=3.8
